{
  "background": null,
  "canCharge": true,
  "cardCost": 1,
  "compensationCR": 0,
  "containersID": [
    "PCL097_KOTS_Coll"
  ],
  "description": "IDS_DESCRIPTION_PCZA020_KOTS",
  "disabled": false,
  "duplicatesCR": 15000,
  "endTime": "",
  "id": 4273970096,
  "index": "PCZA020",
  "isPuzzle": false,
  "name": "PCZA020_Kots",
  "rewards": [
    "<Lootbox boxType=\"PCL072_EPICstd7\" count=\"1\"/>"
  ],
  "startTime": "",
  "subAlbumDiscribtions": [
    [
      "IDS_FIRST_KOTSSUBCOLLECTION_NAME",
      "'aa",
      [
        "<Add type=\"WOWS_PREM\" count=\"1\"/>"
      ]
    ],
    [
      "IDS_SECOND_KOTSSUBCOLLECTION_NAME",
      "'bb",
      [
        "<Add type=\"WOWS_PREM\" count=\"1\"/>"
      ]
    ],
    [
      "IDS_THIRD_KOTSSUBCOLLECTION_NAME",
      "'cc",
      [
        "<Add type=\"WOWS_PREM\" count=\"1\"/>"
      ]
    ],
    [
      "IDS_FOURTH_KOTSSUBCOLLECTION_NAME",
      "'dd",
      [
        "<Add type=\"WOWS_PREM\" count=\"1\"/>"
      ]
    ]
  ],
  "subscribeType": 0,
  "typeinfo": {
    "nation": "Common",
    "species": "CollectionAlbum",
    "type": "Collection"
  }
}