{
  "battleTypes": [
    "PVP",
    "RANKED"
  ],
  "constants": {},
  "enabled": true,
  "events": [],
  "group": false,
  "hidden": true,
  "hiddenCustom": {},
  "hint": "",
  "id": 4240630704,
  "index": "PCH051",
  "isTemplate": false,
  "keepCounters": false,
  "maxShipLevel": 0,
  "minShipLevel": 0,
  "multiple": false,
  "name": "PCH051_STPartisipant",
  "onePerBattle": true,
  "shipCategories": [
    "start",
    "upgradeable",
    "upgradeableExclusive",
    "premium",
    "special",
    "specialUnsellable",
    "peculiar",
    "ultimate",
    "earlyAccess",
    "upgradeableUltimate",
    "demoWithStats",
    "superShip",
    "experimental"
  ],
  "showProgress": false,
  "tags": [],
  "type": "service_medal",
  "typeinfo": {
    "nation": "Common",
    "species": null,
    "type": "Achievement"
  },
  "uiDescription": "",
  "uiHeader": "",
  "uiHideMultiplicity": true,
  "uiName": "ST_PARTICIPANT",
  "uiOutOfDate": false,
  "uiRestrictionIDS": "",
  "uiType": "service_medal"
}