{
  "battleTypes": [
    "PVP",
    "RANKED"
  ],
  "constants": {
    "album": "PCZA011_Ovechkin"
  },
  "enabled": true,
  "events": [
    [
      "fillingAlbum",
      [
        [
          "fillingAlbum",
          "albumName",
          "==",
          "constant",
          "album"
        ]
      ],
      [
        [
          "doAction",
          "done"
        ]
      ]
    ]
  ],
  "group": false,
  "hidden": true,
  "hiddenCustom": {
    "alwaysShowIfAchieved": true
  },
  "hint": "",
  "id": 4089635760,
  "index": "PCH195",
  "isTemplate": false,
  "keepCounters": false,
  "maxShipLevel": 0,
  "minShipLevel": 0,
  "multiple": false,
  "name": "PCH195_FillAlbum_Ovechkin",
  "onePerBattle": true,
  "shipCategories": [
    "start",
    "upgradeable",
    "upgradeableExclusive",
    "premium",
    "special",
    "specialUnsellable",
    "peculiar",
    "ultimate",
    "earlyAccess",
    "upgradeableUltimate",
    "demoWithStats",
    "superShip",
    "experimental"
  ],
  "showProgress": false,
  "tags": [],
  "type": "honorable",
  "typeinfo": {
    "nation": "Common",
    "species": null,
    "type": "Achievement"
  },
  "uiDescription": "",
  "uiHeader": "",
  "uiHideMultiplicity": true,
  "uiName": "COLLECTION_OVECHKIN_COMPLETED",
  "uiOutOfDate": false,
  "uiRestrictionIDS": "",
  "uiType": "common"
}