{
  "angle": 0.0,
  "dist": 0.0,
  "hidePlane": false,
  "id": 4292015440,
  "index": "PVC002",
  "isInvisible": false,
  "launchEffectName": "particles/Empty_FX.xml",
  "linkedGunAngles": [],
  "linkedGunName": null,
  "linkedRotationSpeedCoeff": 1.0,
  "model": "content/gameplay/panamerica/catapult/VC002_Catapult_2/VC002_Catapult_2.model",
  "name": "PVC002_Catapult_2",
  "planeOffsets": {},
  "rotateTime": 0.0,
  "translateDelay": 0.0,
  "typeinfo": {
    "nation": "Pan_America",
    "species": null,
    "type": "Catapult"
  }
}