{
  "RarityCategory": {
    "name": "Uncommon"
  },
  "camouflage": "camo_lagoon_tile",
  "canBuy": true,
  "canCharge": true,
  "canSell": false,
  "costCR": -1,
  "costGold": -1,
  "custom": {},
  "effects": {},
  "filterIsWhitelist": false,
  "hidden": true,
  "hullConfig": {},
  "id": 4233752496,
  "index": "PCEM058",
  "isTemplate": false,
  "isTileflage": true,
  "linkedCamouflage": "PCEC030_Blue_Lagoon",
  "miscFilter": [],
  "miscSubTypeSpecification": {},
  "name": "PCEM058_Tile_Blue_Lagoon",
  "nodesConfig": {},
  "parts": [
    0,
    1,
    2,
    3
  ],
  "peculiarity": "default",
  "peculiarityEffects": {},
  "peculiarityFlag": "",
  "peculiarityModels": {},
  "planesConfig": {},
  "renderSetsStates": {},
  "restrictions": {
    "forbiddenShips": [],
    "levels": [],
    "nations": [],
    "specificShips": [],
    "subtype": []
  },
  "sortOrder": 2147483647,
  "styleEffects": {},
  "styleMiscs": [],
  "subTypes": [],
  "tags": [],
  "typeinfo": {
    "nation": "Common",
    "species": "MSkin",
    "type": "Exterior"
  },
  "unpeculiarCamouflage": "",
  "unpeculiarCamouflageColorSchemeId": 0
}