{
  "Midway_1945": {
    "InnerTrajectory": {
      "backwardResistance": [
        0.0,
        0.0
      ],
      "backwardResistanceTime": [
        0.0,
        0.0
      ],
      "bevelAngle": [
        0.0,
        0.0
      ],
      "bevelRange": [
        0.0,
        0.0
      ],
      "defaultPitch": [
        0.0,
        0.0
      ],
      "defaultYaw": [
        0.0,
        0.0
      ],
      "forwardResistance": [
        0.0,
        0.0
      ],
      "forwardResistanceTime": [
        0.0,
        0.0
      ],
      "horizontalResistance": [
        0.0,
        0.0
      ],
      "horizontalResistanceTime": [
        0.0,
        0.0
      ],
      "ignoreControllerPitch": false,
      "ignoreHeightMultiplier": false,
      "inclineH": [
        0.0,
        0.0
      ],
      "inclineV": [
        0.0,
        0.0
      ],
      "lockOnDefaultPitch": false,
      "lockOnDefaultYaw": false,
      "maxPitch": [
        8.0,
        8.0
      ],
      "maxYaw": [
        0.0,
        0.0
      ],
      "minPitch": [
        -20.0,
        -20.0
      ],
      "minPosY": [
        0.0,
        0.0
      ],
      "minYaw": [
        -0.0,
        -0.0
      ],
      "pitchInfluenceOnHeight": [
        10.0,
        4.0
      ],
      "posCenter": [
        [
          0,
          -3,
          -0.16
        ],
        [
          0,
          -3,
          -0.16
        ]
      ],
      "semiAxisH": [
        5.0,
        5.0
      ],
      "semiAxisV": [
        7.0,
        7.0
      ],
      "verticalResistance": [
        0.0,
        0.0
      ],
      "verticalResistanceTime": [
        0.0,
        0.0
      ],
      "zoomControllerCoef": [
        1.0,
        1.0
      ]
    },
    "OuterTrajectory": {
      "backwardResistance": [
        0.0,
        0.0
      ],
      "backwardResistanceTime": [
        0.0,
        0.0
      ],
      "bevelAngle": [
        0.0,
        0.0
      ],
      "bevelRange": [
        0.0,
        0.0
      ],
      "defaultPitch": [
        0.0,
        0.0
      ],
      "defaultYaw": [
        0.0,
        0.0
      ],
      "forwardResistance": [
        0.0,
        0.0
      ],
      "forwardResistanceTime": [
        0.0,
        0.0
      ],
      "horizontalResistance": [
        0.0,
        0.0
      ],
      "horizontalResistanceTime": [
        0.0,
        0.0
      ],
      "ignoreControllerPitch": false,
      "ignoreHeightMultiplier": false,
      "inclineH": [
        0.0,
        0.0
      ],
      "inclineV": [
        0.0,
        0.0
      ],
      "lockOnDefaultPitch": false,
      "lockOnDefaultYaw": false,
      "maxPitch": [
        8.0,
        8.0
      ],
      "maxYaw": [
        0.0,
        0.0
      ],
      "minPitch": [
        -20.0,
        -20.0
      ],
      "minPosY": [
        0.0,
        0.0
      ],
      "minYaw": [
        -0.0,
        -0.0
      ],
      "pitchInfluenceOnHeight": [
        10.0,
        4.0
      ],
      "posCenter": [
        [
          0,
          0,
          -0.16
        ],
        [
          0,
          0,
          -0.16
        ]
      ],
      "semiAxisH": [
        30.0,
        30.0
      ],
      "semiAxisV": [
        50.0,
        50.0
      ],
      "verticalResistance": [
        0.0,
        0.0
      ],
      "verticalResistanceTime": [
        0.0,
        0.0
      ],
      "zoomControllerCoef": [
        1.0,
        1.0
      ]
    },
    "castZoom": {},
    "hulls": [],
    "tags": "",
    "weapons": []
  },
  "id": 4189734832,
  "index": "PCOL100",
  "inertialRollCoef": 1.0,
  "name": "PCOL100_Midway_1945",
  "rockingCompensationCoef": 1.0,
  "smartZoomAngleCoef": 1.0,
  "typeinfo": {
    "nation": "Common",
    "species": "CameraEllipse",
    "type": "Other"
  }
}